docusign_admin/__init__.py
docusign_admin/apis/__init__.py
docusign_admin/apis/accounts_api.py
docusign_admin/apis/bulk_exports_api.py
docusign_admin/apis/bulk_imports_api.py
docusign_admin/apis/ds_groups_api.py
docusign_admin/apis/identity_providers_api.py
docusign_admin/apis/organizations_api.py
docusign_admin/apis/product_permission_profiles_api.py
docusign_admin/apis/provision_asset_group_api.py
docusign_admin/apis/reserved_domains_api.py
docusign_admin/apis/users_api.py
docusign_admin/client/__init__.py
docusign_admin/client/api_client.py
docusign_admin/client/api_exception.py
docusign_admin/client/api_response.py
docusign_admin/client/configuration.py
docusign_admin/client/auth/__init__.py
docusign_admin/client/auth/oauth.py
docusign_admin/models/__init__.py
docusign_admin/models/add_ds_group_and_users_response.py
docusign_admin/models/add_ds_group_users_response.py
docusign_admin/models/add_user_response.py
docusign_admin/models/add_user_response_account_properties.py
docusign_admin/models/address_information.py
docusign_admin/models/asset_group_account_clone.py
docusign_admin/models/asset_group_account_clone_source_account.py
docusign_admin/models/asset_group_account_clone_target_account.py
docusign_admin/models/asset_group_account_clone_target_account_admin.py
docusign_admin/models/asset_group_account_clones.py
docusign_admin/models/asset_group_account_response.py
docusign_admin/models/asset_group_accounts_response.py
docusign_admin/models/certificate_response.py
docusign_admin/models/clone_error_details.py
docusign_admin/models/delete_membership_request.py
docusign_admin/models/delete_membership_response.py
docusign_admin/models/delete_memberships_request.py
docusign_admin/models/delete_memberships_response.py
docusign_admin/models/delete_response.py
docusign_admin/models/delete_user_identity_request.py
docusign_admin/models/docu_sign_account_domain_model_address.py
docusign_admin/models/domain_response.py
docusign_admin/models/domains_response.py
docusign_admin-2.0.0.dist-info/LICENSE
docusign_admin-2.0.0.dist-info/METADATA
docusign_admin-2.0.0.dist-info/WHEEL
docusign_admin-2.0.0.dist-info/top_level.txt
docusign_admin-2.0.0.dist-info/RECORD
