Metadata-Version: 2.1
Name: docusign-admin
Version: 2.0.0
Summary: Docusign Admin API
Home-page: 
Author-email: devcenter@docusign.com
Keywords: Swagger,Docusign Admin API
License-File: LICENSE
Requires-Dist: urllib3 (>=1.15)
Requires-Dist: six (>=1.8.0)
Requires-Dist: certifi (>=14.05.14)
Requires-Dist: python-dateutil (>=2.5.3)
Requires-Dist: setuptools (>=21.0.0)
Requires-Dist: PyJWT (>=2.0.0)
Requires-Dist: cryptography (>=2.5)
